finalsa/common/lambdas/__init__.py
finalsa/common/lambdas/types.py
finalsa/common/lambdas/app/App.py
finalsa/common/lambdas/app/AppEntry.py
finalsa/common/lambdas/app/__init__.py
finalsa/common/lambdas/common/AppHandler.py
finalsa/common/lambdas/common/__init__.py
finalsa/common/lambdas/common/constants.py
finalsa/common/lambdas/common/exceptions.py
finalsa/common/lambdas/http/HttpHandler.py
finalsa/common/lambdas/http/HttpHeaders.py
finalsa/common/lambdas/http/HttpQueryParams.py
finalsa/common/lambdas/http/HttpResponse.py
finalsa/common/lambdas/http/__init__.py
finalsa/common/lambdas/http/get_handler_filled_args.py
finalsa/common/lambdas/http/parse_methods.py
finalsa/common/lambdas/http/path_methods.py
finalsa/common/lambdas/sqs/SqsEvent.py
finalsa/common/lambdas/sqs/SqsHandler.py
finalsa/common/lambdas/sqs/__init__.py
finalsa/common/lambdas/sqs/get_handler_filled_args.py
finalsa/common/lambdas/test/__init__.py
finalsa_common_lambdas-2.2.1.dist-info/METADATA
finalsa_common_lambdas-2.2.1.dist-info/WHEEL
finalsa_common_lambdas-2.2.1.dist-info/licenses/LICENSE.md
finalsa_common_lambdas-2.2.1.dist-info/RECORD
