Metadata-Version: 2.4
Name: finalsa-common-lambdas
Version: 2.2.1
Summary: Common utilities for Finalsa's AWS Lambda functions
Project-URL: Homepage, https://github.com/finalsa/finalsa-common-lambda
Author-email: Luis Jimenez <luis@finalsa.com>
License: MIT License
License-File: LICENSE.md
Keywords: aws,common,finalsa,lambda,utilities
Requires-Python: >=3.10
Requires-Dist: finalsa-common-logger>=1.0.1
Requires-Dist: finalsa-common-models>=2.0.3
Requires-Dist: finalsa-sqs-client>=2.1.1
Requires-Dist: finalsa-traceability>=1.0.1
Requires-Dist: orjson>=3.10.15
Requires-Dist: pydantic>=2.11.7
